<?xml version = '1.0' encoding = 'UTF-8'?>
<Relation class="oracle.dbtools.crest.model.design.logical.Relation" name="Relation_13" directorySegmentName="seg_0" id="3F8AD871-82AA-3121-BAB7-9D4B4D0D4758">
<createdBy>Rafał</createdBy>
<createdTime>2017-03-22 19:39:27 UTC</createdTime>
<ownerDesignName>Schemat</ownerDesignName>
<engineerTo>
<item key="2DF51BE0-7F03-4B2C-626F-1BEC54405FE6" value="true"/>
</engineerTo>
<sourcePk>FE52D73E-03FB-E8DE-48FE-2C49963E5066</sourcePk>
<identifying>false</identifying>
<optionalSource>true</optionalSource>
<optionalTarget>false</optionalTarget>
<sourceCardinality>1</sourceCardinality>
<sourceEntity>0474E7B4-2393-1A2A-A07D-178EC396B6F7</sourceEntity>
<targetCardinalityString>*</targetCardinalityString>
<targetEntity>46F88FB9-363C-AC9A-A924-CBB079227C01</targetEntity>
<transferable>true</transferable>
<deleteRule>NO ACTION</deleteRule>
</Relation>