<?xml version = '1.0' encoding = 'UTF-8'?>
<Diagram class="oracle.dbtools.crest.swingui.relational.DPVRelational" name="Relational_1" id="97B73412-A221-8493-C49E-C73C765F1B05">
<createdBy>i3olo</createdBy>
<modifiedBy>i3olo</modifiedBy>
<createdTime>2017-03-28 19:22:07 UTC</createdTime>
<autoRoute>false</autoRoute>
<boxInbox>true</boxInbox>
<showLegend>false</showLegend>
<showLabels>false</showLabels>
<showRelAttributes>false</showRelAttributes>
<gridEnabled>false</gridEnabled>
<showGrid>false</showGrid>
<diagramColor>-1</diagramColor>
<display>false</display>
<notation>1</notation>
<objectViews>
<OView class="oracle.dbtools.crest.swingui.relational.TVTable" oid="18633F13-A1C8-0D3F-5FF5-71116FA7E7CF" otype="Table" vid="EB438440-B652-23CA-25E6-13F049365965">
<hideElementsInCurrentOnly>false</hideElementsInCurrentOnly>
<bounds x="833" y="42" width="217" height="86"/>
</OView>
<OView class="oracle.dbtools.crest.swingui.relational.TVTable" oid="223BF371-A898-895F-79B1-CA2E06F2024A" otype="Table" vid="F6200FC2-DEF7-C048-4E73-08A90AE82DC5">
<hideElementsInCurrentOnly>false</hideElementsInCurrentOnly>
<bounds x="454" y="183" width="137" height="104"/>
</OView>
<OView class="oracle.dbtools.crest.swingui.relational.TVTable" oid="2CC41B84-9A88-60D1-BB40-892B2C1C496E" otype="Table" vid="6E0DB6E8-ECD7-BA13-7AA7-4D8F570DB5C9">
<hideElementsInCurrentOnly>false</hideElementsInCurrentOnly>
<bounds x="415" y="659" width="140" height="97"/>
</OView>
<OView class="oracle.dbtools.crest.swingui.relational.TVTable" oid="34BE43ED-DC05-8CED-2215-300DAB9F2C11" otype="Table" vid="D8F79762-EAA3-F9B0-5FCD-B725DDCEEE90">
<hideElementsInCurrentOnly>false</hideElementsInCurrentOnly>
<bounds x="48" y="359" width="165" height="110"/>
</OView>
<OView class="oracle.dbtools.crest.swingui.relational.TVTable" oid="42A29D4F-BBE5-41F9-D9FA-861C0CADE17D" otype="Table" vid="F6625CB8-A8BA-AE50-52B9-8F793BFF9D7F">
<hideElementsInCurrentOnly>false</hideElementsInCurrentOnly>
<bounds x="602" y="428" width="146" height="98"/>
</OView>
<OView class="oracle.dbtools.crest.swingui.relational.TVTable" oid="48B4E578-076A-5932-D393-7FB4381EEF2B" otype="Table" vid="D2A76D0B-9876-6F51-5A5C-3EE322A7E00C">
<hideElementsInCurrentOnly>false</hideElementsInCurrentOnly>
<bounds x="852" y="340" width="170" height="132"/>
</OView>
<OView class="oracle.dbtools.crest.swingui.relational.TVTable" oid="73874A1C-B82D-AED0-F36C-B4CE2EFBC23B" otype="Table" vid="BE449DAF-B4A1-850C-648D-BEA717C67A6B">
<hideElementsInCurrentOnly>false</hideElementsInCurrentOnly>
<bounds x="59" y="657" width="135" height="106"/>
</OView>
<OView class="oracle.dbtools.crest.swingui.relational.TVTable" oid="8498A061-BC53-6F3E-6CE6-2CF13EB72391" otype="Table" vid="3C067558-F4F2-8E53-8837-4685A082B3B9">
<hideElementsInCurrentOnly>false</hideElementsInCurrentOnly>
<bounds x="853" y="207" width="206" height="76"/>
</OView>
<OView class="oracle.dbtools.crest.swingui.relational.TVTable" oid="8DDA6F44-9766-F3D4-9C89-DC12F247A47C" otype="Table" vid="EF1AF01C-8613-91F0-3022-082AC6ABB53D">
<hideElementsInCurrentOnly>false</hideElementsInCurrentOnly>
<bounds x="223" y="104" width="170" height="110"/>
</OView>
<OView class="oracle.dbtools.crest.swingui.relational.TVTable" oid="AF034391-1350-1FC2-680F-23D7F8A8FB64" otype="Table" vid="BB9D74BD-BCF5-B6F0-94A3-5BDC3F67BA0A">
<hideElementsInCurrentOnly>false</hideElementsInCurrentOnly>
<bounds x="311" y="338" width="170" height="139"/>
</OView>
<OView class="oracle.dbtools.crest.swingui.relational.TVTable" oid="BEEC40FB-0AFC-09BB-9A57-A04B9E6314D0" otype="Table" vid="23E41DC6-0BCF-6BB0-9889-E10E78479E2F">
<hideElementsInCurrentOnly>false</hideElementsInCurrentOnly>
<bounds x="321" y="512" width="221" height="110"/>
</OView>
<OView class="oracle.dbtools.crest.swingui.relational.TVTable" oid="DD1D7200-5FDF-1534-F79E-A47224266C8F" otype="Table" vid="CEB965D2-7AD5-91DA-8BED-DA374452077D">
<hideElementsInCurrentOnly>false</hideElementsInCurrentOnly>
<bounds x="583" y="325" width="142" height="71"/>
</OView>
<OView class="oracle.dbtools.crest.swingui.relational.TVTable" oid="DF008FA5-DB5D-A35E-824C-C6EFA5181D0F" otype="Table" vid="2B7A86D9-833D-A801-DD70-62356FB8644A">
<hideElementsInCurrentOnly>false</hideElementsInCurrentOnly>
<bounds x="661" y="202" width="159" height="100"/>
</OView>
</objectViews>
<connectors>
<Connector class="oracle.dbtools.crest.swingui.relational.TVFKRelation" oid="032B7E42-DAC5-4598-1D3A-CC36913927D8" otype="FKIndexAssociation" vid_source="F6625CB8-A8BA-AE50-52B9-8F793BFF9D7F" vid_target="BB9D74BD-BCF5-B6F0-94A3-5BDC3F67BA0A">
<hideElementsInCurrentOnly>false</hideElementsInCurrentOnly>
<lineWidth>1</lineWidth>
<points>
<point x="602" y="452"/>
<point x="481" y="452"/>
</points>
</Connector>
<Connector class="oracle.dbtools.crest.swingui.relational.TVFKRelation" oid="0630714F-5E26-751C-09B3-CE6FADE99178" otype="FKIndexAssociation" vid_source="23E41DC6-0BCF-6BB0-9889-E10E78479E2F" vid_target="BB9D74BD-BCF5-B6F0-94A3-5BDC3F67BA0A">
<hideElementsInCurrentOnly>false</hideElementsInCurrentOnly>
<lineWidth>1</lineWidth>
<points>
<point x="411" y="512"/>
<point x="411" y="477"/>
</points>
</Connector>
<Connector class="oracle.dbtools.crest.swingui.relational.TVFKRelation" oid="12DAD27A-9050-1776-5726-088DD702BC35" otype="FKIndexAssociation" vid_source="BE449DAF-B4A1-850C-648D-BEA717C67A6B" vid_target="6E0DB6E8-ECD7-BA13-7AA7-4D8F570DB5C9">
<hideElementsInCurrentOnly>false</hideElementsInCurrentOnly>
<lineWidth>1</lineWidth>
<points>
<point x="194" y="697"/>
<point x="415" y="697"/>
</points>
</Connector>
<Connector class="oracle.dbtools.crest.swingui.relational.TVFKRelation" oid="411944D2-F366-4728-C67E-DF4BAB704D02" otype="FKIndexAssociation" vid_source="F6200FC2-DEF7-C048-4E73-08A90AE82DC5" vid_target="BB9D74BD-BCF5-B6F0-94A3-5BDC3F67BA0A">
<hideElementsInCurrentOnly>false</hideElementsInCurrentOnly>
<lineWidth>1</lineWidth>
<points>
<point x="477" y="287"/>
<point x="477" y="338"/>
</points>
</Connector>
<Connector class="oracle.dbtools.crest.swingui.relational.TVFKRelation" oid="505E9646-2AEB-5854-13EF-2FB80531F148" otype="FKIndexAssociation" vid_source="2B7A86D9-833D-A801-DD70-62356FB8644A" vid_target="F6200FC2-DEF7-C048-4E73-08A90AE82DC5">
<hideElementsInCurrentOnly>false</hideElementsInCurrentOnly>
<lineWidth>1</lineWidth>
<points>
<point x="661" y="244"/>
<point x="591" y="244"/>
</points>
</Connector>
<Connector class="oracle.dbtools.crest.swingui.relational.TVFKRelation" oid="597F109C-6944-5C66-D7D5-FC4F086D3F1E" otype="FKIndexAssociation" vid_source="D8F79762-EAA3-F9B0-5FCD-B725DDCEEE90" vid_target="BB9D74BD-BCF5-B6F0-94A3-5BDC3F67BA0A">
<hideElementsInCurrentOnly>false</hideElementsInCurrentOnly>
<lineWidth>1</lineWidth>
<points>
<point x="213" y="414"/>
<point x="311" y="414"/>
</points>
</Connector>
<Connector class="oracle.dbtools.crest.swingui.relational.TVFKRelation" oid="84DEA550-4734-3048-BB81-D510BEB63872" otype="FKIndexAssociation" vid_source="D2A76D0B-9876-6F51-5A5C-3EE322A7E00C" vid_target="CEB965D2-7AD5-91DA-8BED-DA374452077D">
<hideElementsInCurrentOnly>false</hideElementsInCurrentOnly>
<lineWidth>1</lineWidth>
<points>
<point x="852" y="368"/>
<point x="725" y="368"/>
</points>
</Connector>
<Connector class="oracle.dbtools.crest.swingui.relational.TVFKRelation" oid="8FF6C4EC-0185-7761-07AA-ED0961DE268E" otype="FKIndexAssociation" vid_source="3C067558-F4F2-8E53-8837-4685A082B3B9" vid_target="D2A76D0B-9876-6F51-5A5C-3EE322A7E00C">
<hideElementsInCurrentOnly>false</hideElementsInCurrentOnly>
<lineWidth>1</lineWidth>
<points>
<point x="949" y="283"/>
<point x="949" y="340"/>
</points>
</Connector>
<Connector class="oracle.dbtools.crest.swingui.relational.TVFKRelation" oid="A608736E-5B44-968D-F7D6-CC303AA9B493" otype="FKIndexAssociation" vid_source="EB438440-B652-23CA-25E6-13F049365965" vid_target="3C067558-F4F2-8E53-8837-4685A082B3B9">
<hideElementsInCurrentOnly>false</hideElementsInCurrentOnly>
<lineWidth>1</lineWidth>
<points>
<point x="951" y="128"/>
<point x="951" y="207"/>
</points>
</Connector>
<Connector class="oracle.dbtools.crest.swingui.relational.TVFKRelation" oid="AA1C050C-8508-B542-132F-187EF3A0D732" otype="FKIndexAssociation" vid_source="EF1AF01C-8613-91F0-3022-082AC6ABB53D" vid_target="BB9D74BD-BCF5-B6F0-94A3-5BDC3F67BA0A">
<hideElementsInCurrentOnly>false</hideElementsInCurrentOnly>
<lineWidth>1</lineWidth>
<points>
<point x="362" y="214"/>
<point x="362" y="338"/>
</points>
</Connector>
<Connector class="oracle.dbtools.crest.swingui.relational.TVFKRelation" oid="AB3228DE-9530-9294-D63B-BB774BA076DE" otype="FKIndexAssociation" vid_source="CEB965D2-7AD5-91DA-8BED-DA374452077D" vid_target="BB9D74BD-BCF5-B6F0-94A3-5BDC3F67BA0A">
<hideElementsInCurrentOnly>false</hideElementsInCurrentOnly>
<lineWidth>1</lineWidth>
<points>
<point x="583" y="377"/>
<point x="481" y="377"/>
</points>
</Connector>
<Connector class="oracle.dbtools.crest.swingui.relational.TVFKRelation" oid="D298CCCA-0EB1-3F4C-592F-6387827F3EAA" otype="FKIndexAssociation" vid_source="D2A76D0B-9876-6F51-5A5C-3EE322A7E00C" vid_target="F6625CB8-A8BA-AE50-52B9-8F793BFF9D7F">
<hideElementsInCurrentOnly>false</hideElementsInCurrentOnly>
<lineWidth>1</lineWidth>
<points>
<point x="852" y="450"/>
<point x="748" y="450"/>
</points>
</Connector>
<Connector class="oracle.dbtools.crest.swingui.relational.TVFKRelation" oid="F9BEED63-90D0-35D8-F07C-3822BD6123A5" otype="FKIndexAssociation" vid_source="6E0DB6E8-ECD7-BA13-7AA7-4D8F570DB5C9" vid_target="23E41DC6-0BCF-6BB0-9889-E10E78479E2F">
<hideElementsInCurrentOnly>false</hideElementsInCurrentOnly>
<lineWidth>1</lineWidth>
<points>
<point x="488" y="659"/>
<point x="488" y="622"/>
</points>
</Connector>
</connectors>
</Diagram>